Advance Digital Design/Lab2/lab2.v
module BitCounter (output reg[3:0] fourBits, input clock, input reset);

integer increment = 1;

always @ (posedge clock)

	begin 

	if (!reset == 1'b1) //high at edge of clock
		fourBits <= fourBits + increment;
	else //low at edge of clock
		fourBits <= 4'b0000;

	end

endmodule

Advance Digital Design/Lab2/lab2_tb.v
`include "lab2.v"

module lab2_tb;
reg clock;
reg reset;
wire [3:0] fourBits;


BitCounter test_b(.fourBits (fourBits),
			 .clock (clock),
			 .reset (reset));

initial	begin

$dumpfile("lab2.vcd");
$dumpvars(0, lab2_tb);

	clock =1;reset = 1; #100;
	clock=1; reset= 0; #100;
	
	#45 $finish; 
	end

always #10 clock = ~clock; // making clock for every 10 ns

endmodule

Advance Digital Design/Lab2/lab2.vcd
$date
	Fri Oct 22 18:15:43 2021
$end
$version
	Icarus Verilog
$end
$timescale
	1s
$end
$scope module lab2_tb $end
$var wire 4 ! fourBits [3:0] $end
$var reg 1 " clock $end
$var reg 1 # reset $end
$scope module test_b $end
$var wire 1 " clock $end
$var wire 1 # reset $end
$var reg 4 $ fourBits [3:0] $end
$var integer 32 % increment [31:0] $end
$upscope $end
$upscope $end
$enddefinitions $end
#0
$dumpvars
b1 %
b0 $
1#
1"
b0 !
$end
#10
0"
#20
1"
#30
0"
#40
1"
#50
0"
#60
1"
#70
0"
#80
1"
#90
0"
#100
b1 !
b1 $
0#
0"
#110
b10 !
b10 $
1"
#120
0"
#130
b11 !
b11 $
1"
#140
0"
#150
b100 !
b100 $
1"
#160
0"
#170
b101 !
b101 $
1"
#180
0"
#190
b110 !
b110 $
1"
#200
0"
#210
b111 !
b111 $
1"
#220
0"
#230
b1000 !
b1000 $
1"
