Advance Digital Design/finalExam/numfive.v
module numberFive (Y, X, V, D1, D2, D3, D4);
        output Y, X, V;
        input D1, D2, D3, D4;
        wire D2_not, one, two;


not G1(D2_not, D2);
and G2(one, D2_not, D1);
or  G3(Y, one, D3);

or G4(two, D2, D3);
or G5(X, D2, D3);

or G6(V, two, D1, D0);
endmodule

Advance Digital Design/finalExam/numfive_tb.v
//Dylan Dennison
//final exam number four test branch
//12/10/21

`include "numfive.v"
`timescale 1ns/1ps


module numberFive_tb;
   reg  D1, D2, D3, D4;
   wire  Y, X, V;

   numberFive test_branch(
        .Y(Y),
        .X(X),
        .V(V),
        .D1(D1),
        .D2(D2),
	.D3(D3),
	.D4(D4)
   );


   initial

     begin

        $dumpfile("numfive.vcd");
        $dumpvars(0, numberFive_tb);

        #10 assign D1 = 0;
        #10 assign D2 = 1;
        #10 assign D3 = 0;
        #10 assign D4 = 1;
        $display("done testing case 0");

	#10 assign D1 = 1;
        #10 assign D2 = 1;
        #10 assign D3 = 0;
        #10 assign D4 = 0;
        $display("done testing case 2");

        #10 assign D1 = 1;
        #10 assign D2 = 0;
        #10 assign D3 = 1;
        #10 assign D4 = 0;
        $display("done testing case 3");

        #10 assign D1 = 1;
        #10 assign D2 = 0;
        #10 assign D3 = 0;
        #10 assign D4 = 1;
        $display("done testing case 4");

        #10 assign D1 = 1;
        #10 assign D2 = 0;
        #10 assign D3 = 0;
        #10 assign D4 = 0;
        $display("done testing case 5");

        #10 assign D1 = 0;
        #10 assign D2 = 0;
        #10 assign D3 = 0;
        #10 assign D4 = 0;
        $display("done testing case 6");

        #10 assign D1 = 1;
        #10 assign D2 = 0;
        #10 assign D3 = 1;
        #10 assign D4 = 0;
        $display("done testing case 7");

	#10 assign D1 = 0;
        #10 assign D2 = 1;
        #10 assign D3 = 1;
        #10 assign D4 = 0;
        $display("done testing case 8");

        #10 assign D1 = 1;
        #10 assign D2 = 1;
        #10 assign D3 = 1;
        #10 assign D4 = 0;
        $display("done testing case 9");

        #10 assign D1 = 1;
        #10 assign D2 = 0;
        #10 assign D3 = 1;
        #10 assign D4 = 1;
        $display("done testing case 10");

        #10 assign D1 = 1;
        #10 assign D2 = 0;
        #10 assign D3 = 0;
        #10 assign D4 = 1;
        $display("done testing case 11");

        #10 assign D1 = 1;
        #10 assign D2 = 1;
        #10 assign D3 = 1;
        #10 assign D4 = 1;
        $display("done testing case 12");

        #10 assign D1 = 0;
        #10 assign D2 = 1;
        #10 assign D3 = 1;
        #10 assign D4 = 1;
        $display("done testing case 13");


        #10 assign D1 = 0;
        #10 assign D2 = 0;
        #10 assign D3 = 1;
        #10 assign D4 = 1;
        $display("done testing case 14");

        #10 assign D1 = 0;
        #10 assign D2 = 0;
        #10 assign D3 = 0;
        #10 assign D4 = 1;
        $display("done testing case 15");

     $finish;

     end

endmodule

Advance Digital Design/finalExam/numfive.vcd
$date
	Fri Dec 10 14:48:33 2021
$end
$version
	Icarus Verilog
$end
$timescale
	1ps
$end
$scope module numberFive_tb $end
$var wire 1 ! Y $end
$var wire 1 " X $end
$var wire 1 # V $end
$var reg 1 $ D1 $end
$var reg 1 % D2 $end
$var reg 1 & D3 $end
$var reg 1 ' D4 $end
$scope module test_branch $end
$var wire 1 ( D0 $end
$var wire 1 $ D1 $end
$var wire 1 % D2 $end
$var wire 1 ) D2_not $end
$var wire 1 & D3 $end
$var wire 1 ' D4 $end
$var wire 1 # V $end
$var wire 1 " X $end
$var wire 1 ! Y $end
$var wire 1 * one $end
$var wire 1 + two $end
$upscope $end
$upscope $end
$enddefinitions $end
#0
$dumpvars
x+
x*
x)
z(
x'
x&
x%
x$
x#
x"
x!
$end
#10000
0*
0$
#20000
1#
0)
1+
1"
1%
#30000
0!
0&
#40000
1'
#50000
1$
#80000
0'
#100000
1!
1*
1)
0+
0"
0%
#110000
1+
1"
1&
#150000
0+
0"
0&
#160000
1'
#200000
0'
#210000
0!
0*
x#
0$
#250000
1!
1*
1#
1$
#270000
1+
1"
1&
#290000
0*
0$
#300000
0)
1%
#330000
1$
#380000
1*
1)
0%
#400000
1'
#430000
0+
0"
0&
#460000
0!
0*
0)
1+
1"
1%
#470000
1!
1&
#490000
0$
#540000
1)
0%
#590000
x#
0!
0+
0"
0&
