Advance Digital Design/Lab4/lab4.v
//Dylan Dennison
//Lab 4
//11/14/21

module lab4code(Alarm, Panic, Enable, Exiting, Window, Door, Garage);

   //varibles
   output reg Alarm;
   input Panic, Enable, Exiting, Window, Door, Garage;


   always @ (Panic or Enable or Exiting or Window or Door or Garage)
   begin

   Alarm <= (((!(Window && Door && Garage)) && (!(Exiting)) && Enable) || Panic); 
   end
endmodule

Advance Digital Design/Lab4/lab4_tb.v
`timescale 1ns/1ps
`include "lab4.v"

module lab4_tb;
   reg  Panic, Enable, Exiting, Window, Door, Garage;
   wire  Alarm;

   lab4code test_branch(
        .Alarm(Alarm),
        .Panic(Panic),
        .Enable(Enable),
        .Exiting(Exiting),
	.Window(Window),
	.Door(Door),
	.Garage(Garage)
   );


   initial

     begin

        $dumpfile("lab4.vcd");
        $dumpvars(0, lab4_tb);
        #10 assign Panic = 0;
        #10 assign Enable = 0;
        #10 assign Exiting = 0;
	#10 assign Window = 0;
	#10 assign Door = 0;
	#10 assign Garage = 0;
        $display("done tesing case 0");
	#10 assign Panic = 1;
        #10 assign Enable = 1;
        #10 assign Exiting = 1;
        #10 assign Window = 1;
        #10 assign Door = 0;
        #10 assign Garage = 0;

        $display("done tesing case 1");
	#10 assign Panic = 0;
        #10 assign Enable = 0;
        #10 assign Exiting = 0;
        #10 assign Window = 1;
        #10 assign Door = 1;
        #10 assign Garage = 1;

        $display("done tesing case 2");
	#10 assign Panic = 0;
        #10 assign Enable = 1;
        #10 assign Exiting = 1;
        #10 assign Window = 1;
        #10 assign Door = 1;
        #10 assign Garage = 1;

        $display("done tesing case 3");
	#10 assign Panic = 0;
        #10 assign Enable = 1;
        #10 assign Exiting = 1;
        #10 assign Window = 0;
        #10 assign Door = 0;
        #10 assign Garage = 0;
	$display("done tesing case 4");
        #10 assign Panic = 0;
        #10 assign Enable = 0;
        #10 assign Exiting = 1;
        #10 assign Window = 0;
        #10 assign Door = 1;
        #10 assign Garage = 0;
	$display("done tesing case 5");
        #10 assign Panic = 0;
        #10 assign Enable = 1;
        #10 assign Exiting = 0;
        #10 assign Window = 0;
        #10 assign Door = 1;
        #10 assign Garage = 0;
	$display("done tesing case 6");
        #10 assign Panic = 1;
        #10 assign Enable = 0;
        #10 assign Exiting = 0;
        #10 assign Window = 0;
        #10 assign Door = 0;
        #10 assign Garage = 0;
	$display("done tesing case 7");


	$finish;

end

endmodule

Advance Digital Design/Lab4/lab4.vcd
$date
	Fri Nov 12 12:49:05 2021
$end
$version
	Icarus Verilog
$end
$timescale
	1ps
$end
$scope module lab4_tb $end
$var wire 1 ! Alarm $end
$var reg 1 " Door $end
$var reg 1 # Enable $end
$var reg 1 $ Exiting $end
$var reg 1 % Garage $end
$var reg 1 & Panic $end
$var reg 1 ' Window $end
$scope module test_branch $end
$var wire 1 " Door $end
$var wire 1 # Enable $end
$var wire 1 $ Exiting $end
$var wire 1 % Garage $end
$var wire 1 & Panic $end
$var wire 1 ' Window $end
$var reg 1 ! Alarm $end
$upscope $end
$upscope $end
$enddefinitions $end
#0
$dumpvars
x'
x&
x%
x$
x#
x"
x!
$end
#10000
0&
#20000
0!
0#
#30000
0$
#40000
0'
#50000
0"
#60000
0%
#70000
1!
1&
#80000
1#
#90000
1$
#100000
1'
#130000
0!
0&
#140000
0#
#150000
0$
#170000
1"
#180000
1%
#200000
1#
#210000
1$
#280000
0'
#290000
0"
#300000
0%
#320000
0#
#350000
1"
#380000
1#
#390000
1!
0$
#430000
1&
#440000
0#
#470000
0"
