Advance Digital Design/Lab3/lab3.v
module labThreeCode (F, X, Y, Z);
	output F;
	input X,Y,Z;
	wire X_not, Y_not, Z_not, XY_not, XY_notZ, X_notYZ_not;


not G1(X_not, X);
not G2(Y_not, Y);
not G3(Z_not, Z);

or G4(XY_not, X, Y_not);

and G5(XY_notZ, XY_not, Z);
and G6(X_notYZ_not, X_not, Y, Z_not);

or G7(F, XY_notZ, X_notYZ_not);

endmodule

Advance Digital Design/Lab3/lab3_tb.v
//Dylan Dennison
//Lab 3 test branch
//10/31/21

`timescale 1ns/1ps
`include "lab3.v"

module lab3_tb;
   reg  X, Y, Z;
   wire  F;

   labThreeCode test_branch(
        .F(F),
        .X(X),
        .Y(Y),
	.Z(Z)
   );


   initial

     begin

        $dumpfile("lab3.vcd");
        $dumpvars(0, lab3_tb);
        #10 assign X = 0;
        #10 assign Y = 0;
	#10 assign Z = 0;
        $display("done tesing case 0");

        #10 assign X = 1;
        #10 assign Y = 0;
	#10 assign Z = 0;
        $display("done tesing case 1");

        #10 assign X = 1;
        #10 assign Y = 1;
	#10 assign Z = 0;
        $display("done tesing case 2");

        #10 assign X = 1;
        #10 assign Y = 0;
	#10 assign Z = 1;
        $display("done tesing case 3");

	#10 assign X = 1;
        #10 assign Y = 1;
        #10 assign Z = 1;
        $display("done tesing case 4");
	
	#10 assign X = 0;
        #10 assign Y = 1;
        #10 assign Z = 0;
        $display("done tesing case 5");

	#10 assign X = 0;
        #10 assign Y = 1;
        #10 assign Z = 1;
        $display("done tesing case 6");

	#10 assign X = 0;
        #10 assign Y = 0;
        #10 assign Z = 1;
        $display("done tesing case 7");

        $finish;

     end

endmodule

Advance Digital Design/Lab3/lab3.vcd
$date
	Thu Oct 28 13:51:44 2021
$end
$version
	Icarus Verilog
$end
$timescale
	1ps
$end
$scope module lab3_tb $end
$var wire 1 ! F $end
$var reg 1 " X $end
$var reg 1 # Y $end
$var reg 1 $ Z $end
$scope module test_branch $end
$var wire 1 ! F $end
$var wire 1 " X $end
$var wire 1 % XY_not $end
$var wire 1 & XY_notZ $end
$var wire 1 ' X_not $end
$var wire 1 ( X_notYZ_not $end
$var wire 1 # Y $end
$var wire 1 ) Y_not $end
$var wire 1 $ Z $end
$var wire 1 * Z_not $end
$upscope $end
$upscope $end
$enddefinitions $end
#0
$dumpvars
x*
x)
x(
x'
x&
x%
x$
x#
x"
x!
$end
#10000
1'
0"
#20000
1%
1)
0(
0#
#30000
0!
1*
0&
0$
#40000
0'
1"
#80000
0)
1#
#110000
1)
0#
#120000
1!
0*
1&
1$
#140000
0)
1#
#160000
0!
0&
1'
0%
0"
#180000
1!
1(
1*
0$
#210000
0!
0(
0*
1$
#230000
1!
1&
1%
1)
0#
